justapypitest/main.py
justapypitest-0.0.1.dist-info/METADATA
justapypitest-0.0.1.dist-info/WHEEL
justapypitest-0.0.1.dist-info/RECORD
