Metadata-Version: 2.1
Name: justapypitest
Version: 0.0.1
Summary: test
License: MIT
Author: Artur Toshev
Author-email: artur.toshev@tum.de
Requires-Python: >=3.9,<4.0
Classifier: License :: OSI Approved :: MIT License
Classifier: Programming Language :: Python :: 3
Classifier: Programming Language :: Python :: 3.9
Classifier: Programming Language :: Python :: 3.10
Classifier: Programming Language :: Python :: 3.11
Requires-Dist: torch (==1.13.1)
